taz/__init__.py
taz/_version.py
taz/aci.py
taz/acr.py
taz/auth.py
taz/blob.py
taz/databricks.py
taz/dls.py
taz/exception.py
taz/http.py
taz/keyvault.py
taz/queue.py
taz/storage_account.py
taz/table.py
tests/__init__.py
tests/config.py
tests/config_template.py
tests/decorator.py
tests/mktemplate.py
tests/test_001_config.py
tests/test_002_auth.py
tests/test_003_keyvault.py
tests/test_005_acr.py
tests/test_006_aci_create.py
tests/test_007_aci_view.py
tests/test_008_aci_delete.py
tests/test_009_blob.py
tests/test_010_dls.py
tests/test_011_dls_glob.py
tests/test_012_table.py
tests/test_013_http.py
tests/test_014_databricks.py
tests/test_014_queue.py
tests/test_aci.py
tests/test_acr.py
tests/test_auth.py
tests/test_blob.py
tests/test_config.py
tests/test_dls.py
tests/test_dls_glob.py
tests/test_keyvault.py
cfa_taz-6.1.0.dist-info/METADATA
cfa_taz-6.1.0.dist-info/WHEEL
cfa_taz-6.1.0.dist-info/top_level.txt
cfa_taz-6.1.0.dist-info/RECORD
